[{"authors":["admin"],"categories":null,"content":"高専で信号を処理してた大学院生(22)になる予定。現在は物理とか情報とか、写真が好きなので画像処理とかも。読書が好きで最近はビジネス書とか気になったのを漁っています。Webデザインの勉強もしています、HTML\u0026amp;CSS かじりたて、これからポートフォリオ作りたいなぁくらいです。最近ヒップホップにハマっています。絶賛サイト移行中。\n","date":-62135596800,"expirydate":-62135596800,"kind":"taxonomy","lang":"en","lastmod":-62135596800,"objectID":"2525497d367e79493fd32b198b28f040","permalink":"https://no74tombi.github.io/authors/admin/","publishdate":"0001-01-01T00:00:00Z","relpermalink":"/authors/admin/","section":"authors","summary":"高専で信号を処理してた大学院生(22)になる予定。現在は物理","tags":null,"title":"Tomoya HIRAKAWA","type":"authors"},{"authors":null,"categories":null,"content":"Flexibility This feature can be used for publishing content such as:\n Online courses Project or software documentation Tutorials  The courses folder may be renamed. For example, we can rename it to docs for software/project documentation or tutorials for creating an online course.\nDelete tutorials To remove these pages, delete the courses folder and see below to delete the associated menu link.\nUpdate site menu After renaming or deleting the courses folder, you may wish to update any [[main]] menu links to it by editing your menu configuration at config/_default/menus.toml.\nFor example, if you delete this folder, you can remove the following from your menu configuration:\n[[main]] name = \u0026quot;Courses\u0026quot; url = \u0026quot;courses/\u0026quot; weight = 50  Or, if you are creating a software documentation site, you can rename the courses folder to docs and update the associated Courses menu configuration to:\n[[main]] name = \u0026quot;Docs\u0026quot; url = \u0026quot;docs/\u0026quot; weight = 50  Update the docs menu If you use the docs layout, note that the name of the menu in the front matter should be in the form [menu.X] where X is the folder name. Hence, if you rename the courses/example/ folder, you should also rename the menu definitions in the front matter of files within courses/example/ from [menu.example] to [menu.\u0026lt;NewFolderName\u0026gt;].\n","date":1536451200,"expirydate":-62135596800,"kind":"section","lang":"en","lastmod":1536451200,"objectID":"59c3ce8e202293146a8a934d37a4070b","permalink":"https://no74tombi.github.io/courses/example/","publishdate":"2018-09-09T00:00:00Z","relpermalink":"/courses/example/","section":"courses","summary":"Learn how to use Academic's docs layout for publishing online courses, software documentation, and tutorials.","tags":null,"title":"Overview","type":"docs"},{"authors":null,"categories":null,"content":"In this tutorial, I\u0026rsquo;ll share my top 10 tips for getting started with Academic:\nTip 1 Lorem ipsum dolor sit amet, consectetur adipiscing elit. Duis posuere tellus ac convallis placerat. Proin tincidunt magna sed ex sollicitudin condimentum. Sed ac faucibus dolor, scelerisque sollicitudin nisi. Cras purus urna, suscipit quis sapien eu, pulvinar tempor diam. Quisque risus orci, mollis id ante sit amet, gravida egestas nisl. Sed ac tempus magna. Proin in dui enim. Donec condimentum, sem id dapibus fringilla, tellus enim condimentum arcu, nec volutpat est felis vel metus. Vestibulum sit amet erat at nulla eleifend gravida.\nNullam vel molestie justo. Curabitur vitae efficitur leo. In hac habitasse platea dictumst. Sed pulvinar mauris dui, eget varius purus congue ac. Nulla euismod, lorem vel elementum dapibus, nunc justo porta mi, sed tempus est est vel tellus. Nam et enim eleifend, laoreet sem sit amet, elementum sem. Morbi ut leo congue, maximus velit ut, finibus arcu. In et libero cursus, rutrum risus non, molestie leo. Nullam congue quam et volutpat malesuada. Sed risus tortor, pulvinar et dictum nec, sodales non mi. Phasellus lacinia commodo laoreet. Nam mollis, erat in feugiat consectetur, purus eros egestas tellus, in auctor urna odio at nibh. Mauris imperdiet nisi ac magna convallis, at rhoncus ligula cursus.\nCras aliquam rhoncus ipsum, in hendrerit nunc mattis vitae. Duis vitae efficitur metus, ac tempus leo. Cras nec fringilla lacus. Quisque sit amet risus at ipsum pharetra commodo. Sed aliquam mauris at consequat eleifend. Praesent porta, augue sed viverra bibendum, neque ante euismod ante, in vehicula justo lorem ac eros. Suspendisse augue libero, venenatis eget tincidunt ut, malesuada at lorem. Donec vitae bibendum arcu. Aenean maximus nulla non pretium iaculis. Quisque imperdiet, nulla in pulvinar aliquet, velit quam ultrices quam, sit amet fringilla leo sem vel nunc. Mauris in lacinia lacus.\nSuspendisse a tincidunt lacus. Curabitur at urna sagittis, dictum ante sit amet, euismod magna. Sed rutrum massa id tortor commodo, vitae elementum turpis tempus. Lorem ipsum dolor sit amet, consectetur adipiscing elit. Aenean purus turpis, venenatis a ullamcorper nec, tincidunt et massa. Integer posuere quam rutrum arcu vehicula imperdiet. Mauris ullamcorper quam vitae purus congue, quis euismod magna eleifend. Vestibulum semper vel augue eget tincidunt. Fusce eget justo sodales, dapibus odio eu, ultrices lorem. Duis condimentum lorem id eros commodo, in facilisis mauris scelerisque. Morbi sed auctor leo. Nullam volutpat a lacus quis pharetra. Nulla congue rutrum magna a ornare.\nAliquam in turpis accumsan, malesuada nibh ut, hendrerit justo. Cum sociis natoque penatibus et magnis dis parturient montes, nascetur ridiculus mus. Quisque sed erat nec justo posuere suscipit. Donec ut efficitur arcu, in malesuada neque. Nunc dignissim nisl massa, id vulputate nunc pretium nec. Quisque eget urna in risus suscipit ultricies. Pellentesque odio odio, tincidunt in eleifend sed, posuere a diam. Nam gravida nisl convallis semper elementum. Morbi vitae felis faucibus, vulputate orci placerat, aliquet nisi. Aliquam erat volutpat. Maecenas sagittis pulvinar purus, sed porta quam laoreet at.\nTip 2 Lorem ipsum dolor sit amet, consectetur adipiscing elit. Duis posuere tellus ac convallis placerat. Proin tincidunt magna sed ex sollicitudin condimentum. Sed ac faucibus dolor, scelerisque sollicitudin nisi. Cras purus urna, suscipit quis sapien eu, pulvinar tempor diam. Quisque risus orci, mollis id ante sit amet, gravida egestas nisl. Sed ac tempus magna. Proin in dui enim. Donec condimentum, sem id dapibus fringilla, tellus enim condimentum arcu, nec volutpat est felis vel metus. Vestibulum sit amet erat at nulla eleifend gravida.\nNullam vel molestie justo. Curabitur vitae efficitur leo. In hac habitasse platea dictumst. Sed pulvinar mauris dui, eget varius purus congue ac. Nulla euismod, lorem vel elementum dapibus, nunc justo porta mi, sed tempus est est vel tellus. Nam et enim eleifend, laoreet sem sit amet, elementum sem. Morbi ut leo congue, maximus velit ut, finibus arcu. In et libero cursus, rutrum risus non, molestie leo. Nullam congue quam et volutpat malesuada. Sed risus tortor, pulvinar et dictum nec, sodales non mi. Phasellus lacinia commodo laoreet. Nam mollis, erat in feugiat consectetur, purus eros egestas tellus, in auctor urna odio at nibh. Mauris imperdiet nisi ac magna convallis, at rhoncus ligula cursus.\nCras aliquam rhoncus ipsum, in hendrerit nunc mattis vitae. Duis vitae efficitur metus, ac tempus leo. Cras nec fringilla lacus. Quisque sit amet risus at ipsum pharetra commodo. Sed aliquam mauris at consequat eleifend. Praesent porta, augue sed viverra bibendum, neque ante euismod ante, in vehicula justo lorem ac eros. Suspendisse augue libero, venenatis eget tincidunt ut, malesuada at lorem. Donec vitae bibendum arcu. Aenean maximus nulla non pretium iaculis. Quisque imperdiet, nulla in pulvinar aliquet, velit quam ultrices quam, sit amet fringilla leo sem vel nunc. Mauris in lacinia lacus.\nSuspendisse a tincidunt lacus. Curabitur at urna sagittis, dictum ante sit amet, euismod magna. Sed rutrum massa id tortor commodo, vitae elementum turpis tempus. Lorem ipsum dolor sit amet, consectetur adipiscing elit. Aenean purus turpis, venenatis a ullamcorper nec, tincidunt et massa. Integer posuere quam rutrum arcu vehicula imperdiet. Mauris ullamcorper quam vitae purus congue, quis euismod magna eleifend. Vestibulum semper vel augue eget tincidunt. Fusce eget justo sodales, dapibus odio eu, ultrices lorem. Duis condimentum lorem id eros commodo, in facilisis mauris scelerisque. Morbi sed auctor leo. Nullam volutpat a lacus quis pharetra. Nulla congue rutrum magna a ornare.\nAliquam in turpis accumsan, malesuada nibh ut, hendrerit justo. Cum sociis natoque penatibus et magnis dis parturient montes, nascetur ridiculus mus. Quisque sed erat nec justo posuere suscipit. Donec ut efficitur arcu, in malesuada neque. Nunc dignissim nisl massa, id vulputate nunc pretium nec. Quisque eget urna in risus suscipit ultricies. Pellentesque odio odio, tincidunt in eleifend sed, posuere a diam. Nam gravida nisl convallis semper elementum. Morbi vitae felis faucibus, vulputate orci placerat, aliquet nisi. Aliquam erat volutpat. Maecenas sagittis pulvinar purus, sed porta quam laoreet at.\n","date":1557010800,"expirydate":-62135596800,"kind":"page","lang":"en","lastmod":1557010800,"objectID":"74533bae41439377bd30f645c4677a27","permalink":"https://no74tombi.github.io/courses/example/example1/","publishdate":"2019-05-05T00:00:00+01:00","relpermalink":"/courses/example/example1/","section":"courses","summary":"In this tutorial, I\u0026rsquo;ll share my top 10 tips for getting started with Academic:\nTip 1 Lorem ipsum dolor sit amet, consectetur adipiscing elit. Duis posuere tellus ac convallis placerat. Proin tincidunt magna sed ex sollicitudin condimentum.","tags":null,"title":"Example Page 1","type":"docs"},{"authors":null,"categories":null,"content":"Here are some more tips for getting started with Academic:\nTip 3 Lorem ipsum dolor sit amet, consectetur adipiscing elit. Duis posuere tellus ac convallis placerat. Proin tincidunt magna sed ex sollicitudin condimentum. Sed ac faucibus dolor, scelerisque sollicitudin nisi. Cras purus urna, suscipit quis sapien eu, pulvinar tempor diam. Quisque risus orci, mollis id ante sit amet, gravida egestas nisl. Sed ac tempus magna. Proin in dui enim. Donec condimentum, sem id dapibus fringilla, tellus enim condimentum arcu, nec volutpat est felis vel metus. Vestibulum sit amet erat at nulla eleifend gravida.\nNullam vel molestie justo. Curabitur vitae efficitur leo. In hac habitasse platea dictumst. Sed pulvinar mauris dui, eget varius purus congue ac. Nulla euismod, lorem vel elementum dapibus, nunc justo porta mi, sed tempus est est vel tellus. Nam et enim eleifend, laoreet sem sit amet, elementum sem. Morbi ut leo congue, maximus velit ut, finibus arcu. In et libero cursus, rutrum risus non, molestie leo. Nullam congue quam et volutpat malesuada. Sed risus tortor, pulvinar et dictum nec, sodales non mi. Phasellus lacinia commodo laoreet. Nam mollis, erat in feugiat consectetur, purus eros egestas tellus, in auctor urna odio at nibh. Mauris imperdiet nisi ac magna convallis, at rhoncus ligula cursus.\nCras aliquam rhoncus ipsum, in hendrerit nunc mattis vitae. Duis vitae efficitur metus, ac tempus leo. Cras nec fringilla lacus. Quisque sit amet risus at ipsum pharetra commodo. Sed aliquam mauris at consequat eleifend. Praesent porta, augue sed viverra bibendum, neque ante euismod ante, in vehicula justo lorem ac eros. Suspendisse augue libero, venenatis eget tincidunt ut, malesuada at lorem. Donec vitae bibendum arcu. Aenean maximus nulla non pretium iaculis. Quisque imperdiet, nulla in pulvinar aliquet, velit quam ultrices quam, sit amet fringilla leo sem vel nunc. Mauris in lacinia lacus.\nSuspendisse a tincidunt lacus. Curabitur at urna sagittis, dictum ante sit amet, euismod magna. Sed rutrum massa id tortor commodo, vitae elementum turpis tempus. Lorem ipsum dolor sit amet, consectetur adipiscing elit. Aenean purus turpis, venenatis a ullamcorper nec, tincidunt et massa. Integer posuere quam rutrum arcu vehicula imperdiet. Mauris ullamcorper quam vitae purus congue, quis euismod magna eleifend. Vestibulum semper vel augue eget tincidunt. Fusce eget justo sodales, dapibus odio eu, ultrices lorem. Duis condimentum lorem id eros commodo, in facilisis mauris scelerisque. Morbi sed auctor leo. Nullam volutpat a lacus quis pharetra. Nulla congue rutrum magna a ornare.\nAliquam in turpis accumsan, malesuada nibh ut, hendrerit justo. Cum sociis natoque penatibus et magnis dis parturient montes, nascetur ridiculus mus. Quisque sed erat nec justo posuere suscipit. Donec ut efficitur arcu, in malesuada neque. Nunc dignissim nisl massa, id vulputate nunc pretium nec. Quisque eget urna in risus suscipit ultricies. Pellentesque odio odio, tincidunt in eleifend sed, posuere a diam. Nam gravida nisl convallis semper elementum. Morbi vitae felis faucibus, vulputate orci placerat, aliquet nisi. Aliquam erat volutpat. Maecenas sagittis pulvinar purus, sed porta quam laoreet at.\nTip 4 Lorem ipsum dolor sit amet, consectetur adipiscing elit. Duis posuere tellus ac convallis placerat. Proin tincidunt magna sed ex sollicitudin condimentum. Sed ac faucibus dolor, scelerisque sollicitudin nisi. Cras purus urna, suscipit quis sapien eu, pulvinar tempor diam. Quisque risus orci, mollis id ante sit amet, gravida egestas nisl. Sed ac tempus magna. Proin in dui enim. Donec condimentum, sem id dapibus fringilla, tellus enim condimentum arcu, nec volutpat est felis vel metus. Vestibulum sit amet erat at nulla eleifend gravida.\nNullam vel molestie justo. Curabitur vitae efficitur leo. In hac habitasse platea dictumst. Sed pulvinar mauris dui, eget varius purus congue ac. Nulla euismod, lorem vel elementum dapibus, nunc justo porta mi, sed tempus est est vel tellus. Nam et enim eleifend, laoreet sem sit amet, elementum sem. Morbi ut leo congue, maximus velit ut, finibus arcu. In et libero cursus, rutrum risus non, molestie leo. Nullam congue quam et volutpat malesuada. Sed risus tortor, pulvinar et dictum nec, sodales non mi. Phasellus lacinia commodo laoreet. Nam mollis, erat in feugiat consectetur, purus eros egestas tellus, in auctor urna odio at nibh. Mauris imperdiet nisi ac magna convallis, at rhoncus ligula cursus.\nCras aliquam rhoncus ipsum, in hendrerit nunc mattis vitae. Duis vitae efficitur metus, ac tempus leo. Cras nec fringilla lacus. Quisque sit amet risus at ipsum pharetra commodo. Sed aliquam mauris at consequat eleifend. Praesent porta, augue sed viverra bibendum, neque ante euismod ante, in vehicula justo lorem ac eros. Suspendisse augue libero, venenatis eget tincidunt ut, malesuada at lorem. Donec vitae bibendum arcu. Aenean maximus nulla non pretium iaculis. Quisque imperdiet, nulla in pulvinar aliquet, velit quam ultrices quam, sit amet fringilla leo sem vel nunc. Mauris in lacinia lacus.\nSuspendisse a tincidunt lacus. Curabitur at urna sagittis, dictum ante sit amet, euismod magna. Sed rutrum massa id tortor commodo, vitae elementum turpis tempus. Lorem ipsum dolor sit amet, consectetur adipiscing elit. Aenean purus turpis, venenatis a ullamcorper nec, tincidunt et massa. Integer posuere quam rutrum arcu vehicula imperdiet. Mauris ullamcorper quam vitae purus congue, quis euismod magna eleifend. Vestibulum semper vel augue eget tincidunt. Fusce eget justo sodales, dapibus odio eu, ultrices lorem. Duis condimentum lorem id eros commodo, in facilisis mauris scelerisque. Morbi sed auctor leo. Nullam volutpat a lacus quis pharetra. Nulla congue rutrum magna a ornare.\nAliquam in turpis accumsan, malesuada nibh ut, hendrerit justo. Cum sociis natoque penatibus et magnis dis parturient montes, nascetur ridiculus mus. Quisque sed erat nec justo posuere suscipit. Donec ut efficitur arcu, in malesuada neque. Nunc dignissim nisl massa, id vulputate nunc pretium nec. Quisque eget urna in risus suscipit ultricies. Pellentesque odio odio, tincidunt in eleifend sed, posuere a diam. Nam gravida nisl convallis semper elementum. Morbi vitae felis faucibus, vulputate orci placerat, aliquet nisi. Aliquam erat volutpat. Maecenas sagittis pulvinar purus, sed porta quam laoreet at.\n","date":1557010800,"expirydate":-62135596800,"kind":"page","lang":"en","lastmod":1557010800,"objectID":"1c2b5a11257c768c90d5050637d77d6a","permalink":"https://no74tombi.github.io/courses/example/example2/","publishdate":"2019-05-05T00:00:00+01:00","relpermalink":"/courses/example/example2/","section":"courses","summary":"Here are some more tips for getting started with Academic:\nTip 3 Lorem ipsum dolor sit amet, consectetur adipiscing elit. Duis posuere tellus ac convallis placerat. Proin tincidunt magna sed ex sollicitudin condimentum.","tags":null,"title":"Example Page 2","type":"docs"},{"authors":[],"categories":null,"content":" Click on the Slides button above to view the built-in slides feature.   Slides can be added in a few ways:\n Create slides using Academic\u0026rsquo;s Slides feature and link using slides parameter in the front matter of the talk file Upload an existing slide deck to static/ and link using url_slides parameter in the front matter of the talk file Embed your slides (e.g. Google Slides) or presentation video on this page using shortcodes.  Further talk details can easily be added to this page using Markdown and $\\rm \\LaTeX$ math code.\n","date":1906549200,"expirydate":-62135596800,"kind":"page","lang":"en","lastmod":1906549200,"objectID":"96344c08df50a1b693cc40432115cbe3","permalink":"https://no74tombi.github.io/talk/example/","publishdate":"2017-01-01T00:00:00Z","relpermalink":"/talk/example/","section":"talk","summary":"An example talk using Academic's Markdown slides feature.","tags":[],"title":"Example Talk","type":"talk"},{"authors":null,"categories":null,"content":"","date":1584403200,"expirydate":-62135596800,"kind":"page","lang":"en","lastmod":1584403200,"objectID":"8cdd7498a35c8d2b4bee937c524179c8","permalink":"https://no74tombi.github.io/project/html-training/","publishdate":"2020-03-17T00:00:00Z","relpermalink":"/project/html-training/","section":"project","summary":"WEBデザインの練習を兼ねて、html \u0026 CSS でサイトを制作します。制作物へのリンク。","tags":["Web-Design","Hobby"],"title":"HTML\u0026CSS 精進の記録","type":"project"},{"authors":[],"categories":["tech"],"content":"こんにちは, hiratchi です. 皆さんも, 締切前日にWord で書いていた文書をTeXで書き直さなくてはならないことって多いと思います(ない). 僕もそうでした. この記事では僕が約30分（ネット環境に大きく依存）で行った超速であり超適当なLaTeX 導入を備忘録的にメモします. パッケージマネージャとしてapt を採用しているUbuntu とかでも出来るような気がしてますがやるのは自己責任でお願いします.\n導入 なんと言ってもtexliveですよね. ってことでとりあえずインストールします.\n$sudo apt install texlive-full  ネットの環境によってはかなり時間がかかるし通信量もごっそり持ってかれます(5GB程度). 僕は学校のネット使ってtexlive-fullをインストールしました, ごめんなさい. 日本語関連ものだけでいい！って人は上記の代わりに以下で良いです.\n$sudo apt install texlive-lang-japanese  さて, 上記のいずれかをインストールできたらもう終わったようなもんです. 僕はいつもTeX文書を書くときにはTeXstudio を使っています. スペルチェックもできるし, ウィザードで図の挿入や簡単な表の挿入もできちゃいます. ので, こいつを入れちゃいます.\nsudo apt install texstudio  これで完了です. コマンドラインでtexstudio と打てば起動するはずです.\n設定 実際に起動し, TeXをコンパイルしようとするとエラーがドヒャっと出てきて, ちびると思いますのでTeXstudio の設定もしときます. いろいろなサイトを参考にできちゃう人はそれでいいです. Options \u0026gt; Configure TeXstudio... で設定いじれますのでココをいろいろ変えてきます.\nまずはCommandsタブです. ここでは, LatexやBibTexのコマンド等を設定します. デフォルトから変わってないところのほうが多いです. 具体的には,\n LaTeX: latex を uplatex に変更, -src を -synctex=1 に変更 DviPdf: dvipdfm を dvipdfmx -f textfonts.map %.dvi に変更 BibTeX: bibtex を upbibtex に変更 Biber: biber を biber --bblencoding=utf8 -u -U --output_safechars に変更  こんな感じでしょうか, DviPdf の設定に関して言えば, フォントを埋め込む必要のない方は「dvipdfm を dvipdfmx に変更」と読み替えておいてください.\n次にビルドの設定をします. TeXstudio ではコンパイルして画面の右側にプレビューを表示してくれます. Build タブに切り替えて, Build \u0026amp; View の部分を DVI-\u0026gt;PDF Chain に変更しておきます.\n僕がやった設定は以上です.\n最後に 備忘録的記事なので必然的に雑記事になってしまいました. 結果的に誰得な記事になっちゃいましたが, 急にTeX 環境が必要になったあなたの力になれたら幸いです.\n","date":1579680899,"expirydate":-62135596800,"kind":"page","lang":"en","lastmod":1579680899,"objectID":"6111fbaffc68b74f6768c715ecd92d92","permalink":"https://no74tombi.github.io/post/latex_preparation/","publishdate":"2020-01-22T17:14:59+09:00","relpermalink":"/post/latex_preparation/","section":"post","summary":"MX Linux にLatex 環境をぱぱっと導入する記事です. MX Linux はDebian ベースのOSですので, パッケージマネージャとしてapt を採用しているOS を使っている方も参考になるのではないでしょうか. それと僕はCUIでTeXのコンパイルはしない主義(できないだけ)なので, TeXstudio 入れて気軽にTeX を始めました. そんな記事です.","tags":["latex","環境構築","texstudio"],"title":"論文締切前日にやる超速TeX環境構築","type":"post"},{"authors":[],"categories":["tech"],"content":"こんにちは, hiratchi です. この記事では, どのようにしてこのサイトを作ったかを解説します. 言わずもかな GitHub と Hugo という静的サイトジェネレータを用いて約20分で出来上がります. 記事はMarkdown で書けるので, 普段 Latex とか使うタイプの人ならば親和性が高いと思います.\n 目次：サイトを作るまで　  Git, Hugo のインストール  GitHub に2つのリポジトリ(コード管理用、公開用)を作成・クローン  サイトの作成・テーマの適用  自分なりにサイトをカスタマイズ  deploy.sh の作成\u0026amp;実行   以下, 順に解説していきます.\n0.Git,Hugoのインストール Git は言わずともしれたコード管理ツールの一つです(知らない人は コチラ). アカウントないよって人は ココで登録しましょう. Git については コチラを参照して, 入れてみてください.\nHugo はGO言語(自分もよく知らない)で書かれた静的サイトジェネレータです. Markdown で記事がかけたり, 特に知識がなくてもテーマが豊富なので, すぐにいい感じのサイトが作れます. Hugo についても同様にコチラ( Linux, Mac, Windows)を参照して, 入れてみてください.\n1.GitHubに2つのリポジトリを作成・クローン  この記事に倣って, コードの管理用のリポジトリと, デプロイ(公開)用のレポジトリを作ります. 自分のGitHub にアクセスして, 管理用の blog_src(名前は任意)と, デプロイ用の \u0026lt;ユーザ名\u0026gt;.github.io(指定)というレポジトリを作成してください. あとでクローンするのでREADMEの作成オプションは有効化しといてね. んで, ローカルに blog_src の方をクローンしましょう.\n$git clone https://github.com/\u0026lt;ユーザ名\u0026gt;/blog_src.git  基本的にはこっちをカスタマイズしていきます, もう片方は自分でいじることはほとんどありません.\n2.サイトの作成・テーマの適用 いよいよサイトを作ります, といっても難しいことは何一つとしてしません. blog_src フォルダのある階層で\n$hugo new site blog_src --force  とやります. hugo new site [サイトの名前] で hugo は新しいサイトを作ってくれます. 今回は空でない blog_src フォルダに作っちゃうので--force としていますが, あんまりよろしくはないです. こうして, めでたくサイトの作成は完了です.\n次にテーマを適用します. ココを見ればわかるように, めっちゃテーマが公開されてます. 好きなのを選んで, 作りましょう. このブログは academia というテーマを使っていますが, 今回は Cupper を使ってみます. どのテーマを使っても良いです, 基本的には下の画像のようにテーマのページの Installation ってとこに従えばだいたいできます. blog_src に入って以下を実行します.\n$git submodule add https://github.com/zwbetz-gh/cupper-hugo-theme.git themes/cupper-hugo-theme  これで, テーマを適用しました. hugo server コマンドでローカルのサーバを立ち上げることができます.\n$ hugo server -t cupper-hugo-theme : : : Web Server is available at http://localhost:39181/ (bind address 127.0.0.1)  一番最後に出てきたアドレスをブラウザのアドレスバーにコピペして, どんなページができているか確認してみましょう. (-t オプションはテーマを指定してサーバを立ち上げます.) こんな感じになったらとりあえず成功です. Ctrl+C でサーバーを閉じてあげましょう.\n3.自分なりにサイトをカスタマイズ ここまできたらあとはあなたの好きにしましょう. 基本的にはconfig.toml ファイルをいじってサイトの構成を変えていきます. 今回はブログを作るのに最低限必要だと思うものを以下においておきます.\nconfig.toml\n# サイトの基本設定 title = \u0026quot;サイト名\u0026quot; baseurl = \u0026quot;https://hiratchi.github.io/\u0026quot; copyright = \u0026quot;(c) {year} Tomoya HIRAKAWA\u0026quot; # 言語設定 defaultContentLanguage = \u0026quot;ja\u0026quot; # 出力後の \u0026lt;html lang=\u0026quot;\u0026quot;\u0026gt; の部分 hasCJKLanguage = true # trueにすると、日中韓の言語で文字カウントとかが正しく動作する hrefTargetBlank = true theme = \u0026quot;cupper-hugo-theme\u0026quot; paginate = 10 # Number of items per page in paginated lists. enableEmoji = true enableGitInfo = true #記事の更新日 [menu] # メニューバーの設定 [[menu.nav]] name = \u0026quot;Home\u0026quot; # 表示される名称 url = \u0026quot;/\u0026quot; # 参照するアドレス weight = 1 [[menu.nav]] name = \u0026quot;Blog\u0026quot; # 表示される名称 url = \u0026quot;/post/\u0026quot; # 参照するアドレス weight = 2 [[menu.nav]] name = \u0026quot;About\u0026quot; # 表示される名称 url = \u0026quot;/about/\u0026quot; # 参照するアドレス weight = 3 [[menu.nav]] name = \u0026quot;Categories\u0026quot; # 表示される名称 url = \u0026quot;/categories/\u0026quot; # 参照するアドレス weight = 4 [taxonomies] tag = \u0026quot;tags\u0026quot; category = \u0026quot;categories\u0026quot;  また, themes/exampleSite/content にある themes/exampleSite/content/_index.md と, themes/exampleSite/content/about.md をルートフォルダの/content にコピーしておきます. ここで, $hugo server してあげると\u0026hellip; こんな感じになっていると思います. なんか出来上がってきましたね. もうお察しかと思われますが, content フォルダ内の.md ファイルが表示されます. このファイルをいじってあげれば自分好みのHome, About 画面を作れますよ. しかしこの状態でBlog をクリックすると404エラーが出てしまいます. だって,　記事何も書いてないんだもの\u0026hellip; ってことで, 記事を作成しましょう!\n$hugo new post/first.md  実行するとcontent/postにfirst.mdというファイルができていると思います. これが記事の正体です. こいつをこんなふうに書いてみましょう.\ncontent/post/first.md\n--- title: \u0026quot;初めての記事\u0026quot; date: 2020-01-09T19:18:36+09:00 draft: false --- こんにちは、ようこそブログへ！  これで, 記事が完成しました. draft は true だと, 「下書き」扱いになって, 普段は表示されません.\n$hugo serverを行ってBlog を開いてみると\u0026hellip; 記事がきちんと投稿されている！\nってことでまとめると, blog の記事を作成するには\nhugo new post/\u0026lt;ファイル名\u0026gt;.md  を行えば良いんです, 簡単でしょ, うん. markdown ファイルの上部は, 記事のメタデータになっていて, タグやカテゴリも追加できます.\n例\n--- title: \u0026quot;初めての記事\u0026quot; date: 2020-01-09T19:18:36+09:00 draft: false tags: ['タグ1', 'タグ2', 'タグ3'] --- こんにちは、ようこそブログへ！  調べたらいろいろ出てきますのでお試しあれ.\n4.deploy.shの作成\u0026amp;実行 ここからは作ったサイトをネット上に公開していきます. まずは下準備から, blog_src の中で以下を実行します.\n# publicディレクトリを削除。 $ rm -rf public # publicディレクトリを公開先リポジトリとしてサブモジュール化する(最初の設定のときに1回だけ行う) $ git submodule add -b master git@github.com:\u0026lt;ユーザ名\u0026gt;/\u0026lt;ユーザ名\u0026gt;.github.io.git public  次に, blog_srcフォルダ直下にdeploy.shを作ります. 自分がなにかblog_src フォルダ内のファイルをいじってサイトに変更を加えたあとに, このdeploy.shを実行することで, ネット上に公開されているサイトに変更が反映されます.\ndeploy.sh\necho -e \u0026quot;\\033[0;32mDeploying updates to GitHub...\\033[0m\u0026quot; # Build the project. hugo -t academic # Go To Public folder cd public # Add changes to git. git add . # Commit changes. msg=\u0026quot;rebuilding site `date`\u0026quot; if [ $# -eq 1 ] then msg=\u0026quot;$1\u0026quot; fi git commit -m \u0026quot;$msg\u0026quot; # Push source and build repos. git push origin master # Come Back up to the Project Root cd .. # Commit source repository changes git add . git commit -m \u0026quot;$msg\u0026quot; git push  最後にこのファイルを実行してあげましょう.\n$./ deploy.sh  最後に, ブラウザでhttps://\u0026lt;ユーザ名\u0026gt;.github.io にアクセスしてみてください. できていましたか?\nこれでブログが出来上がったはずです. あとは記事を投稿したりだとか, テーマを変えてみたりだとかいろいろ好きにやっちゃってください. ググればたくさん出てきます.\n 参考  サルでもわかるGit入門\n HUGOでブログ作成 → GitHub Pagesで公開する手順\n HUGOをインストールしてみた\n テーマ Cupper のカスタマイズ\n","date":1578547968,"expirydate":-62135596800,"kind":"page","lang":"en","lastmod":1578547968,"objectID":"c1b60d9e2136a1919630dc3ea4ef9bb4","permalink":"https://no74tombi.github.io/post/howtomakeblog/","publishdate":"2020-01-09T14:32:48+09:00","relpermalink":"/post/howtomakeblog/","section":"post","summary":"この記事では, どのようにしてこのサイトを作ったかを解説します. 言わずもかな GitHub と Hugo という静的サイトジェネレータを用いて約20分で出来上がります. 記事はMarkdown で書けるので, 普段 Latex とか使うタイプの人ならば親和性が高いと思います.","tags":["git","hugo","blog"],"title":"Hugo+GitHubでブログを公開する","type":"post"},{"authors":null,"categories":["book"],"content":"書籍情報 title: アイディアのレッスン\nauthor: 外山滋比古\npublisher: ちくま文庫\nアイディアの基本  アイディアとは生活的でいっそう軽い新しい考えのこと 発見や発明のもとになる アメリカは30年前からコンピュータのできない創造性に重きを置く教育  まずは考える  学校は知ることを目的とする、記憶型思考 日本人の英語の口癖“I think\u0026hellip;” 日本人はコピーキャットと呼ばれる コンピュータという記憶の怪物 アイディアには子供のような頭  工夫して思いつく  工夫する、問題解決の良い方法、手段を探す、色々と試みる 工夫は努力と成果が比例しない シェイクスピア「思いのように迅速に」  価値ある考えとは  日本人はものにこだわり、ものにありがたみを感じる、無形の価値には鈍感 病院の診察や弁護士への相談料が良い例 情報も経済的価値はある 菊池寛の『文藝春秋』は巻頭にエッセイ、これまでの雑誌の巻頭論文を一新するスタイル、座談会記事の創設  アイディアを生むwant  偶然に左右されるアイディアの生涯 必要は発明の母なり(Necessity is the mother of invention)、を少し変えてwantは発明の母なりとする want: 欲求、欠乏、必要  「プロ的アイディア」と「アマ的アイディア」  実際的目的を持って生まれた、実際的な仕事になる「プロ的アイディア」 企画部とかがそれにあたる アイディアのためのアイディアを求める「アマ的アイディア」 実利的な利益を目指すことなしにただ新しいこと、物を考え作り上げることを喜ぶ  至る所に隠れているアイディア  命名は立派なアイディア、綽名も然り 賭け事好きのサンドイッチ伯爵(イギリス)がゲームを中断せずに食事、いまのサンドイッチ 主婦が買い物に出かけて食事を頭の中で思い浮かべるのもアイディア チグハグはアイディアの乏しい証拠  ユーモア・冗談  ユーモアはアイディアで成立し、アイディアで面白くなる 事実だけ、知識だけだと面白くもおかしくもない 純粋で直線的、物事に囚われがちな人はユーモアのセンスを欠くことが多い 自由で、囚われない、面白さを追求する精神が必要  アイディアはところを選ぶ  机に向かうより歩くとき、ゆうやかな坂道でとか言う人 当面の問題と縁のない本を読むこととか言う人 転地の効果、芭蕉の奥の細道 考えようによっては散歩も転地  いつ、どこから？  他のことをしているとき モーツァルトは玉突き中に「魔笛」のアイディア ウィリアム・ハミルトンは散歩中に数学の発見、化学者のケクレはロンドンバスの二階に乗ってる時に新しい理論 逆にアイディアを待ち受ける アルキメデスは入浴中に比重の原理「ユーリーカ」 関心を広くしなければならない 文案を寝るのに適した場所、三上→馬上、枕上、厠上、現代で言うと通勤電車の中、寝てるとき、トイレの中 三中→夢中、散歩中、入浴中  浮かんだらメモ  一度逃すと次はない 要点だけ、絶えずとれる状況にしとく 半分眠っているような時間はアイディアの好む時間 メモを見返し、整理することが肝要  アイディア作りには忘却が必要  頭を掃除しないとアイディアはやってこない 忘れる頭は発想には良い頭、ものに囚われない発想 眠りが最も効果的な頭の掃除 ちょっとした疲労にはコーヒー・ブレイク 夢中になることも大切、畑違いの人と夢中で交流 緊張と弛緩から創造が生まれる  アイディア作りは休むに似たり  真似たくなるのなら、人のものを見たりしない 読書を途中で止める、人の考えを自分の考えたことのように思い出すと危ない ある程度考えたら休むこと  アイディアは誤りの中から  誤りはクリエイティブ フレミング博士のペニシリン、使用済みのブドウ球菌の培地に青カビが混入、カビの周りだけ繁殖が止まっていたことからペニシリンが 理屈に合わないからと頭から否定しないこと 常識を疑う謙虚さ  アイディアの作り方 以下、『思考の整理学』との重複があるので雑にまとめます。\n ブレインストーミング   課題、問題を設定し各々が解決の方法を考えだす。誰がどんなことを言っても水を差さない。アイディアは臆病で自信欠如なものだから。聞き上手・褒め上手が求められる。\n延長線・慣性の法則   「その先」を考える、例えば、化学の物質の最小単位とされる原子、この先を考える。延長線的想像力の知的生産。 思考の持続を利用する、寂しさは「感情の残像」\nセレンディピティ 発酵させる カクテルにする たとえる 結合させる   無関係なもの、触媒を作用させる。\n類推する   アナロジーをあてはめる、比例式の例。\nバリエーションを作る   自分の考えをよその、前からある他の考えを背景にして作り出すと借りた考えと一緒になって全体がまとまり、着想に。\n入れ替える   主客を入れ替えることで注目外の考えを前面に押し出した新しいアイデアに。\n","date":1574402239,"expirydate":-62135596800,"kind":"page","lang":"en","lastmod":1574402239,"objectID":"576a5742560e49e8035606dddf9750ed","permalink":"https://no74tombi.github.io/post/bookidea-lesson/","publishdate":"2019-11-22T14:57:19+09:00","relpermalink":"/post/bookidea-lesson/","section":"post","summary":"『アイディアのレッスン』という本を読んだメモ。","tags":["memo","book"],"title":"読書ノート「アイディアのレッスン」","type":"post"},{"authors":null,"categories":["book"],"content":"Amazon Prime でタダで読めた、面白かったです。量子力学勉強したくなった、そんな本です。\n書籍情報 title: [世界の仕組みを物理学で知る]（http://www.yamakei.co.jp/products/2818130100.html）\nauthor: 松原隆彦\npublisher: 山と渓谷社\nウォール街で活躍する物理学者  ジェームズ・シモンズが創設した投資会社ルネッサンス・テクノロジーズ(ルネッサンス) 金融や経済のバックグラウンドを持つ人は一切雇わずに、物理、数学、統計の博士を多く雇う クオンツ: コンピュータと高度数理モデルを駆使して投資戦略を考える専門家 物理で株価を予測は「熱力学」、「統計力学」、「量子力学」が応用？ 世界の心理を全て知っていて未来を完全予測できるもの「ラプラスの魔物」 電波にとって不導体は透明で、導体は鏡  物理学者の正体  『なぜだろうなぜかしら』シリーズ 物理学とは複雑なものをなるべく単純化して理解しようとする学問 物が下に落ちる、なぜ？ 万有引力(ニュートン)により、実はものと地球が引き合っている、ではなぜ引き合う？ 空間が曲がっているから引き合う(アインシュタイン)、ではなぜ空間は曲がる？ というような果てしない「なぜ？」を突き詰めてそれ以上の理由がない法則を見つけ出すのが物理学の目的 世の中に働く４つの力「引力」「電磁気力」「強い力」「弱い力」 原子核中で陽子と中性子をくっつける「強い力」 中性子が陽子に変わるなど粒子に変化を起こす「弱い力」 身の回りの出来事は「引力」か「電磁気力」で説明可能 「弱い力」と「電磁気力」は統一できた 「強い力」と「電磁気力」と「弱い力」を統一したい、カミオカンデは「陽子崩壊現象」を確かめるため しかし棚ぼた的にニュートリノを発見、副産物的。 力の統一で現在有力な「超ひも理論」 超ひも理論の正しさの証明には銀河系と同じくらい巨大な加速器が必要 アインシュタインはアマチュア学者だった  空の上の物理学  雲は落ちない、物凄く空気抵抗を受けやすいから、また上昇気流などで浮きっぱなし 空はなぜ青い？波長の長い赤はまっすぐ進みやすく、短い青や紫は散乱しやすい 夕焼け、朝焼けはなぜオレンジ？太陽から大気の中を通る距離が増えて、散乱しやすい青は途中で失われ、真っ直ぐに進みやすい赤っぽい光が届く 太陽からもらうエネルギーと、宇宙に放出するエネルギーのバランスが崩れている 地軸はなぜ傾いている？偶然で、逆に垂直であるという理由もない 月の重力により地軸の傾きは安定、四季も月のおかげ 星が自転するのはなぜ？物質同士の衝突弾合体により回転が生まれる、ゼロになることの方が少ない、また、宇宙に摩擦はないから 惑星の探し方、中心の星(恒星)を見てその手前を惑星が横切るとき少し暗くなるのでそれを観測するか、恒星の周りを惑星が回ると少なからず恒星も揺れる、それを観測  光の話  赤はなぜ赤色か？その物が赤色以外の光を吸収し赤色の光だけ反射し、その光が目に届く 吸収された光は熱エネルギーに変わる、黒は熱を持ちやすい 熱を持てば電磁波を放射 水面で反射した光のほとんどは水平方向の偏光に変わる、偏光グラスの原理 左目と右目は見える物が違う、3D映像は右眼と左眼に少しずつズレた映像を見せる 同じ赤だが見え方は？RGBの錐体細胞の分布によるが心理的要因も大きい 錯視は脳が経験や周りの情報を融合してできる  素粒子、原子、分子  火傷は分子運動過多の仕業、凍傷ま逆ではあるが分子運動過少の仕業 原子発見はブラウン運動から、アインシュタインが理論的に導いた、ジャン・ペランが理論の正当性を確認 ボルツマンは陰で原子論を独自に組み立てるものの先を行き過ぎていたため受け入れられず、晩年に精神を病み自殺 原子は「原子核と電子」、「陽子と中性子と電子」、「クォーク」実はクォークが物質を構成する最小単位で原子ではなかった クォークとクォーク、陽子と中性子は「強い力」でくっつく、これは電磁気力の１００倍で、その正体は「グルーオン」 クォークは宇宙ができた直後から存在、未来永劫おそらく変わらない 意識はどこから生まれるのか、意識が電気信号ならば自分が自分である必要性はなくなる  相対性理論  GPSも相対論、衛星側には原子時計なので物凄く正確 動いている物の時間は遅く進む「特殊相対性理論」 重力がかかると時間は遅く進む「一般相対性理論」 光の媒体「エーテル」は存在しない、光は真空中でも伝わる  特殊相対性理論  止まっている人が動いている人を見ると時間が間延びするし、動いている人は縮んで見える、ローレンツ変換で説明可能 しかし動いている人から見て止まっている人も動く、お互いに時間が間延びしている どちらが正しいということはなく、単に相対的な物で自分の感じる時間に変化は何もない  一般相対性理論   「重力」を「時間と空間の歪み」で説明\n  トランポリンの例\n  時空間の性質は「リーマン幾何学」で正確に表すことができる\n  アインシュタインは「頭の中」で生み出した天才\n  時空の歪みは太陽のそばをかすめる遠くの星の観測で明らかに、日食のタイミングで\n  スカイツリーの最上階と地上の時間は1日で100億分の1秒ズレる\n  ポツダム天文台長カール・シュヴァルツシルトがアインシュタイン方程式からブラックホール発生の可能性を初めて示す\n  ブラックホール中心の「時空の特異点」の先は？現在の物理学では説明できない\n  マイケル天神モリスとキップ・ソーンがワームホール安定の答えを示す\n  量子論の世界  紫外線はエネルギーが高い、エネルギーは波長に反比例 赤外線はエネルギーが低いので体の表面で止まる 量子:波と粒子の性質を併せ持つ小さな塊、エネルギーの最小単位 ヤングの二重スリット実験によって明らかに プランクはエネルギーの離散性を示す、エネルギーには最小単位がありその整数倍しか取らない アインシュタインは光そのもののエネルギーに最小値があると仮定し、光子を提唱、光電効果(ある金属に光を当てると電子が飛び出す)の発見 太陽光発電は光子がぶつかり電子を飛び出させ電気を流す マックス・ボルンによる量子の確率解釈 仮想通貨は素因数分解による暗号化、量子コンピュータが出たらすぐに解けちゃう  量子の計算方法  「観測できないことは考えてはいけない」ハイゼンベルクの方程式 「波として計算する」シュレディンガー方程式 「世界が分裂しながら同時進行する」ファインマン方程式  ","date":1574315839,"expirydate":-62135596800,"kind":"page","lang":"en","lastmod":1574315839,"objectID":"f11443f74386a746d9db36a980efbc1b","permalink":"https://no74tombi.github.io/post/booksekai-physics/","publishdate":"2019-11-21T14:57:19+09:00","relpermalink":"/post/booksekai-physics/","section":"post","summary":"『世界の仕組みを物理学で知る』という本を読んだメモ。","tags":["memo","book"],"title":"読書ノート「世界の仕組みを物理学で知る」","type":"post"},{"authors":null,"categories":["book"],"content":"最近YouTube 見ているメンタリストのDaigo さんの本を読みました。\n書籍情報 title: 週40時間の自由をつくる超時間術\nauthor: メンタリスト Daigo\npublisher: 実務教育出版\n# 物理的な時間がないという勘違い  労働時間は実は減り続けている 思ったよりも忙しくないという事実を認める 細かい締め切りはネガティブな感情を利用したものでダメージとなることも 忙しいという口癖をやめる、現在に集中できない 「忙しい」のかわりに「活動的だ」などを使う  やるべきことが多すぎるという勘違い  やるべきことが多いと安心感 15分の振り返りが効果的 作業量よりも生産性 やるべきことが多い、は、正しい選択ができていない 大きな成果を出すために行動を絞り込む  忙しい人は仕事ができるという勘違い  忙しさと有能さは比例しない 一日に違うジャンルの作業を行うとタスクを達成する確率が下がる 週25-30時間の労働がベスト 多くても週に40時間 忙しい人ほど体調を崩す 大多数の人の「働くほど成果がてる」といった思い込み 権力には時間感覚を変えさせる効果がある 時間が足りないパニックになると負のスパイラル 時間を捨てることを恐れない、行動での自己管理 エピクロス「明日をもっとも必要としない者が、最も快く明日に立ち向かう」  ゴールコンフリクトを正す  いくつもの欲望や目標が混在し、時間不足の感覚を起こす  ゴールコンフリクトの三種  わかっているけどやらない 思い込み 無知のコンフリクト  コンフリクトリストの作り方  目標を10個書き出す 重要な5個をピックアップ その目標の障害を書き出す 障害をコンフリクトのパターンに分類   わかってるけどやらない、にはやるしかない仕組みを作る 思い込み、には自分の悩みを他人事のように見る「セルフディスタンシング」 または「メンタル・タイムトラベル」問題が未来にどうなってるかを考える、割と絶望的な 無知コンフリクトには、「知的謙遜」すなわち「自分の知識の限界を知ること」  ソクラテス式問答法  明確化: 問題の具体的なゴールは？ 前提: 問題についてわかっていないことは？ 証拠: 今の答えを事実だと考えた理由は？ 起源: 今の自分の考え方やアイデアはどこからきたのか？ 結果: 問題を試したらどんな効果が？ 視点: 他の人はどう答えるか？ 仮定: 今の答えの代わりになる答えは？  時間汚染  マルチタスクは時間感覚を歪める 前もって決めた感覚でタスクをシフト、１つのタスクで30分がベストでどんなに調子が良くても潔く切り替えること メール確認の時間、回数を決めておく 全く違う能力のマルチタスクであれば何の問題もない   ウォーキングマシンを使いながら読書 料理と電話 皿洗いとオーディオブック   全ての作業を同じ環境でやらない、作業と場所をセットでまとめておく できなかった作業は溜めない 1時間を超えて仕事はしない  呼吸について  5秒吸う、6秒吐くを10セットでストレス減少 スクリーン無呼吸に注意、ブルーライトの影響 深呼吸の習慣づけ 息を吸った倍の時間で吐くパワーブリージングが有効  レベル別呼吸法  等感覚呼吸法 腹式呼吸 片鼻呼吸 カパーラバーティ スダルシャンクリヤ 詳しくは本書参照  リフレーミング  嫌な状況を前向きに解釈 感覚のラベリングを行う、自分の体の変化を言語化 深呼吸、感覚ラベリング、リフレーミングの手順 インナーパーソナリティを作る、リストアップすることでリフレーミングがうまくいく セネカ(古代ギリシャの哲人)の不安対処法「怒りを感じた時は正反対の行動を、顔の筋肉をリラックス、声を穏やかに、ゆっくり歩く」 不安を認めながら、不安がないかのように振る舞う 時間のプレッシャーがきたら「ワクワク、興奮」を声に出す  親切  他人への親切は時間感覚がのびる、自己効力感   相手に共感 相手のミスに寛容に 他人にポジティブな影響を与える 他人に害がある行為は全力で避ける わがままを我慢   ドーパミンによるヘルパーズハイ   自分を犠牲にしない 週一五善 親切は年に100時間 自分にとって意味ある親切を  スモールゴール  小さな目標を設定、嘘の達成感でも良い   最長でも20分の目標、5分くらいから 成功率が80%くらい 自分の達成度をノートに記録、ゴールに直接関連するものだけ、パブリックコミットメント(友人やSNS,blogで公開)、アナログ優先、デジタルは入力が簡単すぎる   障害ベースのスモールゴール   スモールゴールを紙に書く ゴール達成時のメリット３つ ゴールを達成する際の障害を３つ 最も大きな障害は？ その対策を決めておこう  自然  「自然」は私たちの心を日常から切り離す 自分が小さな存在だと感じ、客観的な視点を持ち、トラブルに冷静に対応 まずは1日60秒の動画タイム、ナショナルジオグラフィックなどなど 15分だけ自然の中で(公園なども可)ボーッとする、ウォーキングと組み合わせる グリーンエクササイズ、簡単なのがガーデニング  ストレス解消法  一時停止リマインダー、一時停止マークを目のつく場所に貼っておくだけで、不安やストレスを感じそうになったらそれ見て深呼吸 背筋を伸ばす 楽しい記憶を思い出す 貧乏ゆすり、なんでもいいので体をリズミカルに ガムを噛む 不安になる時間を決めとく テトリス 動物動画 スプリント・インターバル・トレーニング(SIT)、週に３回以内   30秒全力で体を動かす 3分の休憩 30秒全力で体を動かす、ガチレベルに追い込むこと   太陽の光を浴びる 筆記開示   ネガティブな体験を思い出す 8分だけ沸いた感情を紙に書き出す   心拍トラッキングタスク お笑い動画を見る パワーナップ、10分から30分 休暇の計画を立てる、できるだけ細かく コーピング・レパートリー、すなわち自分にとって有効なストレス対策をリスト化、できるだけお金と時間がかからないもの ビジュアル・アナログ・スケールを活用、筆記開示と同様に自分の感情を客観的に 自動思考キャッチトレーニング、自分の反射的なネガティブ思考を捕まえる クールチャレンジ   好きなだけ熱いシャワー 冷たいシャワーを30秒から90秒 好きなだけ熱いシャワー   慈悲のプラクティス、本書参照  やってはいけないストレス対策  ギャンブル ショッピング、自分の物を買うのはダメ、他人のため、体験、お金で時間を買うのは良い タバコ 酒、少量なら良い 過食 ゲーム・ネット、ドーパミンによる心の疲労  職場の時間汚染対策  通勤時間はできるだけ短く、肥満や離婚の原因に 在宅勤務による、満足度アップ、ストレス減少、パフォーマンス増加 自転車通勤はストレス減、エクササイズの場に 通勤に強い人は目的意識がある   今日のゴールは？ 目標のために必要な作業は？ 作業中に起こりうるトラブルは？   インターバル読書   好きな本を3分読む 頭の中で要約する  プレップ・ドゥ・レビュー プレップ  これから何しようとしてるか 行動の理由、目標、目的は？ 行動はどのように行うべきか？ 行動に関わるのは誰？ 目的達成に必要な人や情報は？  ドゥ 淡々と実行する\nレビュー   いつどれくらいの時間で目標達成したか\n  準備通りに実行できたか？\n  前に比べて何が変わった？\n  準備を実行してわかったことは？\n  次に同じことが起きてもっとうまくやれることは？\n  ブレインストーミングは死んだ、ブレインライティングへ\n  最後に 定期的に時間を捨てるのは参考になる。スマホの電源を切り、誰の邪魔も入らないところへ。\n","date":1574229439,"expirydate":-62135596800,"kind":"page","lang":"en","lastmod":1574229439,"objectID":"a287f66905422013045b1ef4a3e9245f","permalink":"https://no74tombi.github.io/post/bookdaigo-time/","publishdate":"2019-11-20T14:57:19+09:00","relpermalink":"/post/bookdaigo-time/","section":"post","summary":"メンタリストDaigoさん著『超時間術』という本を読んだメモ。","tags":["memo","book"],"title":"読書ノート「超時間術」","type":"post"},{"authors":null,"categories":["book"],"content":"本を読む時間ができたので、読書メモをしようかと。\n書籍情報 title: 思考の整理学\nauthor: 外山滋比古\npublisher: 筑摩書房\nグライダー  学校では先生と教科書に引っ張られて勉強する、グライダーのようなものだ。飛行機とグライダーは似ているが、グライダーは自力で飛ぶことはできない。 学校はグライダー訓練所、優等生はグライダーとして優秀。 こどもは労せず詩人であり小発明家。学校で教育されて散文的になり人真似が上手くなる。 人間は花を見て枝葉を見ない。 新しい文化の創造には飛行機能力が必要。  不幸な逆説  昔の塾や道場は教えるのを拒む。学習意欲を高めるため。 すぐに全てを教え込まない。 秘術は隠す、愛弟子は真似ようとする。結果としてグライダー卒業、飛行機人間に。 今の学校は教えすぎ、親切でありすぎる。  朝飯前  朝の頭の方が夜より優秀っぽい。 朝飯の前に簡単でもなんでもないことがさっさとできてしまう「朝飯前」 朝の頭は能率が良く楽天的。 ブランチ(breakfast+lunch)で朝食を遅らせると昼まで朝飯前の時間。 いかにして朝飯前の時間を長くするか。  発酵  素材を発酵させる、寝させることでテーマができる。 見つめる鍋は煮えない、しばらく忘れること。 異本論について、Aを読んで理解するのは異本A’で決してAそのものではない(六法全書は異本を少ししか許さない) 熟したテーマは向こうからやってくる  寝させる  英語成語: “over sleep” 一晩寝て考える 「朝から晩まで考え続けた」はこだわりができ、大局を見失う。 幸運は寝て待つ  カクテル  「ひとりでは多すぎる。ひとりでは、全てを奪ってしまう。」(アメリカの女流作家ウィラ・キャザー) 「ひとり」は恋人のこと １つだけでは、多すぎる。  エディターシップ  イギリスの詩人批評家、T・S・エリオットは「人生に一度も本を書かなかった」 編纂するのであって、書き下ろしがない 独立した表現が全体の一部になると性格が変わる。 何をどういう配列で並べるか。 「詩とは最も良き語を最も良き順序に置いたものである」  触媒  新しいことを考えるのに自分の頭から絞り出せる、は愚問。 既に存在するものを結びつけることで新しいものが生まれる。 焦る、緊張するのはものを考えるのに不要、心をゆったり、自由に。 優れたカクテルを作るには小さな自我は抑えて良いものと良いものが結びつくように。 発想の母体は触媒としての個性。  アナロジー  慣性の法則 視覚における残像現象 心理的残像 外国語などで辞書引くと言葉と言葉が離れ離れになるが、思い切って早く読むとかえってよくわかる、修辞的残像  セレンディピティ  潜水艦の機関音を捉える目的の実験がイルカの交信の発見に 行きがけの駄賃のようにして生まれる発見(セレンディピティ) 語源は「セイロン(現スリランカ)の三王子」という童話、よくものをなくし、探し物をするが狙うものは一向に出てこず、予期しないものを掘り出す。 セイロンはセレンディップと呼ばれていた。 周辺的関心\u0026gt;中心的関心  情報のメタ化  人為としての情報は高次の抽象化へ昇華 思考の整理は低次の思考をメタ化していく、それをしなければ単なる思いつき  スクラップ  たまには捨てる。 贅肉を落としていかないと動きが取れなくなる。  カードノート  出典、何という本の何ページからとか。 見出しをつけておくこと、内容を簡潔、的確に示す。  つんどく法  テーマに関連のある文献を集められるだけ集める。 頭の中に記録していく。記録した安心感が忘却を促進。 はじめの一歩が最も時間を食うのでより標準的なものを読む。 読み終えたらなるべく早くまとめの文章。 自分の頭をノートに、カードに。  手帳とノート  手帳の中でアイデアは小休止、寝かせる。 メタ・ノートでさらに抽象化。  整理  人間の頭は倉庫として考えられてきたが、新しいことを考え出さなければならないのも事実。 睡眠が必要。  忘却のさまざま  転地効果でリフレッシュ。 やけ酒とかはNG 難しい本をわかろうとして読むとかえって落ち着く。 忘れる時は別のことをする。 汗を流す、血の巡りをよくする。  時の試練  流行の色眼鏡をかけて見てしまう。 時間をかけて変わるべきところは変わらせる必要がある、いわば時の試練。 優れたものは語り継がれる。  すてる  「知識それ自体が力である」ベーコン 収穫逓減の法則に似た、知識逓減、はじめは勉強すればするほど能率が上がっていくが、かなり精通すると壁につき当たる。 不要なものはどんどんすてる。 意識的にすてるのが整理。  とにかく書いてみる  気軽に書いてみる。 気負わないこと、構想はゆるくても良い。 文章は欲を出すと逆効果で、書けないと思ってる時でも、もう書けると自分に言い聞かす。 書いているうちに頭に筋道ができる。 書き出したら先を急ぐ、全速力の自転車が少しくらいの障害をものともせずに直進するように。 推敲する。  テーマと題名  大雑把な題名が好まれる。 修飾語を多くつけると表現は弱くなる、修飾を多くすると厳密になる場合もあるが、不用意に行うと伝達性を損なう、厭味になることも。 三上章(あきら)の『象は鼻が長い』は一見童話に見えるが、実は二重人格を扱った日本文法論。  ホメテヤラネバ  ピグマリオン効果: 40人をA,Bに分ける(平均点は同じに調整)。Aには採点した答案を返すが、Bにはテストの成績は良かったと告げる。何度か繰り返すとBの方が点数が高くなる。  しゃべる  原稿は黙って書くが、読み直しは音読する。声は思いの外、賢明。  ","date":1573538239,"expirydate":-62135596800,"kind":"page","lang":"en","lastmod":1573538239,"objectID":"19b52c0eec5b1acb29e2404a87fb051d","permalink":"https://no74tombi.github.io/post/bookshikou/","publishdate":"2019-11-12T14:57:19+09:00","relpermalink":"/post/bookshikou/","section":"post","summary":"『思考の整理学』という本を読んだメモ。","tags":["memo","book"],"title":"読書ノート「思考の整理学」","type":"post"},{"authors":[],"categories":[],"content":"Create slides in Markdown with Academic  Academic | Documentation\n Features  Efficiently write slides in Markdown 3-in-1: Create, Present, and Publish your slides Supports speaker notes Mobile friendly slides   Controls  Next: Right Arrow or Space Previous: Left Arrow Start: Home Finish: End Overview: Esc Speaker notes: S Fullscreen: F Zoom: Alt + Click  PDF Export: E   Code Highlighting Inline code: variable\nCode block:\nporridge = \u0026quot;blueberry\u0026quot; if porridge == \u0026quot;blueberry\u0026quot;: print(\u0026quot;Eating...\u0026quot;)   Math In-line math: $x + y = z$\nBlock math:\n$$ f\\left( x \\right) = ;\\frac{{2\\left( {x + 4} \\right)\\left( {x - 4} \\right)}}{{\\left( {x + 4} \\right)\\left( {x + 1} \\right)}} $$\n Fragments Make content appear incrementally\n{{% fragment %}} One {{% /fragment %}} {{% fragment %}} **Two** {{% /fragment %}} {{% fragment %}} Three {{% /fragment %}}  Press Space to play!\nOne  Two  Three \n A fragment can accept two optional parameters:\n class: use a custom style (requires definition in custom CSS) weight: sets the order in which a fragment appears   Speaker Notes Add speaker notes to your presentation\n{{% speaker_note %}} - Only the speaker can read these notes - Press `S` key to view {{% /speaker_note %}}  Press the S key to view the speaker notes!\n Only the speaker can read these notes Press S key to view    Themes  black: Black background, white text, blue links (default) white: White background, black text, blue links league: Gray background, white text, blue links beige: Beige background, dark text, brown links sky: Blue background, thin dark text, blue links    night: Black background, thick white text, orange links serif: Cappuccino background, gray text, brown links simple: White background, black text, blue links solarized: Cream-colored background, dark green text, blue links   Custom Slide Customize the slide style and background\n{{\u0026lt; slide background-image=\u0026quot;/img/boards.jpg\u0026quot; \u0026gt;}} {{\u0026lt; slide background-color=\u0026quot;#0000FF\u0026quot; \u0026gt;}} {{\u0026lt; slide class=\u0026quot;my-style\u0026quot; \u0026gt;}}   Custom CSS Example Let\u0026rsquo;s make headers navy colored.\nCreate assets/css/reveal_custom.css with:\n.reveal section h1, .reveal section h2, .reveal section h3 { color: navy; }   Questions?  Ask\n Documentation\n","date":1549324800,"expirydate":-62135596800,"kind":"page","lang":"en","lastmod":1549324800,"objectID":"0e6de1a61aa83269ff13324f3167c1a9","permalink":"https://no74tombi.github.io/slides/example/","publishdate":"2019-02-05T00:00:00Z","relpermalink":"/slides/example/","section":"slides","summary":"An introduction to using Academic's Slides feature.","tags":[],"title":"Slides","type":"slides"},{"authors":["Tomoya HIRAKAWA","Kazuki Chigita","Yoshimitsu Kuroki"],"categories":null,"content":" Click the Cite button to import publication metadata into your reference management software.   ","date":-62135596800,"expirydate":-62135596800,"kind":"page","lang":"en","lastmod":-62135596800,"objectID":"163cd0f5e4790670812e458e47bb561e","permalink":"https://no74tombi.github.io/publication/iwait2018/","publishdate":"0001-01-01T00:00:00Z","relpermalink":"/publication/iwait2018/","section":"publication","summary":"This paper describes a distributed compressed sensing method of HSI (Hyper Spectral Image). Similar to conventional methods, our method transfers computational load from encoder to decoder, and divides images into key and non-key frames. In video coding schemes, decoders interpolate non-key frames using motion vector or optical flow referring decoded key frames. However, the adjacent frames in wavelength domain have strong correlation at the same spacial positions. The PNSR of interpolated non-key frames would be high; then, our method applies ADMM (Alternating Direction Method of Multipliers) not only to reconstruct key and non-key frames but also to design the dictionaries of non-key frames. Experimental results show that the PSNR values of our method are about 3 to 5 dB higher than those of the method using DCT (Discrete Cosine Transform) for the dictionaries.","tags":null,"title":"Distributed compressed hyper spectral image sensing using ADMM","type":"publication"},{"authors":["Tomoya HIRAKAWA","Shohei Kubota","Yoshimitsu Kuroki"],"categories":null,"content":" Click the Cite button to import publication metadata into your reference management software.   ","date":-62135596800,"expirydate":-62135596800,"kind":"page","lang":"en","lastmod":-62135596800,"objectID":"4d824ba50600a094c0ac5d88da5f9006","permalink":"https://no74tombi.github.io/publication/ispacs2019/","publishdate":"0001-01-01T00:00:00Z","relpermalink":"/publication/ispacs2019/","section":"publication","summary":"Best Student Paper Award","tags":null,"title":"Image Classification by Multilayer Feature Extraction Based on Nuclear Norm Minimization","type":"publication"},{"authors":["Tomoya HIRAKAWA","Yoshimitsu Kuroki"],"categories":null,"content":" Click the Cite button to import publication metadata into your reference management software.   ","date":-62135596800,"expirydate":-62135596800,"kind":"page","lang":"en","lastmod":-62135596800,"objectID":"9cc8a844d6194f010b47789877327a1f","permalink":"https://no74tombi.github.io/publication/gcce2019/","publishdate":"0001-01-01T00:00:00Z","relpermalink":"/publication/gcce2019/","section":"publication","summary":"This paper describes a novel multilayer-sparse-representation based image classification. This method designs a dictionary for sparse coefficients of each layer with ADMM (Alternating Direction Method of Multipliers) referring training images. For the classification stage, sparse coefficients should also be calculated with ADMM for test images, which needs computational burden. To reduce the burden, this work proposes to project inputs onto dictionary atoms of each layer instead of solving sparse coefficients. This alternative method is inspired by CNNs (Convolutional Neural Networks), and is also faster than solving sparse coefficients. Experimental results show that our method can predict coefficient vectors faster than the conventional methods with almost equivalent classification accuracy.","tags":null,"title":"Image classification on projection based multilayer sparse representation","type":"publication"},{"authors":["Tomoya HIRAKAWA","Kuntopng Wararatpanya","Yoshimitsu Kuroki"],"categories":null,"content":" Click the Cite button to import publication metadata into your reference management software.   ","date":-62135596800,"expirydate":-62135596800,"kind":"page","lang":"en","lastmod":-62135596800,"objectID":"412abb8f896789f0ec76995ef70e88f1","permalink":"https://no74tombi.github.io/publication/iwait2019/","publishdate":"0001-01-01T00:00:00Z","relpermalink":"/publication/iwait2019/","section":"publication","summary":"Being motivated by the Saak (Subspace approximation with augmented kernels) transform, we propose an image recognition scheme using multi-layer sparse feature extraction with a convex solver ADMM (Alternating Direction Method of Multipliers). The Saak transform consists of a multi-layer PCA (Principal Component Analysis) and S/P (Sign-to-Position) conversion to avoid sign confusion. This paper adopts sparse representation instead of PCA and also compares the S/P conversion with the activation function ReLU (Rectified Linear Unit), which is realized by involving the projection mapping onto the non-negative set in convex formulas. The Saak transform uses PCA not only for feature extraction but also for dimension compression of feature vectors. We expect that our method does not need the dimension compression since sparse representation compresses features more than PCA. Experimental results on the MNIST and Fashion-MNIST dataset show that the proposed method is equivalent to the Saak transform in recognition accuracy, and that our method can make features more sparse and extract features that have high discriminant power locally.","tags":null,"title":"Image recognition using multi-layer sparse feature extraction with ADMM","type":"publication"}]